Metadata-Version: 2.1
Name: teste_lmacon
Version: 1.0
Summary: first_py
Requires-Dist: botcity-framework-core<1.0,>=0.4.0
